os_client_config/__init__.py
os_client_config/cloud_config.py
os_client_config/config.py
os_client_config/constructors.json
os_client_config/constructors.py
os_client_config/defaults.json
os_client_config/defaults.py
os_client_config/exceptions.py
os_client_config/tests/__init__.py
os_client_config/tests/base.py
os_client_config/tests/test_cloud_config.py
os_client_config/tests/test_config.py
os_client_config/tests/test_environ.py
os_client_config/tests/test_import_vendors.py
os_client_config/tests/test_init.py
os_client_config/vendors/__init__.py
os_client_config-2.3.0.dist-info/AUTHORS
os_client_config-2.3.0.dist-info/LICENSE
os_client_config-2.3.0.dist-info/METADATA
os_client_config-2.3.0.dist-info/WHEEL
os_client_config-2.3.0.dist-info/pbr.json
os_client_config-2.3.0.dist-info/top_level.txt
os_client_config-2.3.0.dist-info/RECORD
